MANIFEST.in
README.rst
requirements.txt
setup.py
test_requirements.txt
python_trakt.egg-info/PKG-INFO
python_trakt.egg-info/SOURCES.txt
python_trakt.egg-info/dependency_links.txt
python_trakt.egg-info/requires.txt
python_trakt.egg-info/top_level.txt
trakt/__init__.py
trakt/api.py
trakt/errors.py
trakt/tv.py
trakt/tests/__init__.py
trakt/tests/test_api.py
trakt/tests/test_trakt.py