Metadata-Version: 1.0
Name: python-trakt
Version: 0.1
Summary: Python interface to trakt.tv API
